enhancerai/__init__.py
enhancerai/pl/__init__.py
enhancerai/pl/basic.py
enhancerai/pp/__init__.py
enhancerai/pp/_basic.py
enhancerai/tl/__init__.py
enhancerai/tl/basic.py
enhancerai-0.0.1.dist-info/METADATA
enhancerai-0.0.1.dist-info/WHEEL
enhancerai-0.0.1.dist-info/licenses/LICENSE
enhancerai-0.0.1.dist-info/RECORD
