Metadata-Version: 2.1
Name: EnhancerAI
Version: 0.0.1
Summary: A deep learning toolkit for investigating the gene regulatory code
Project-URL: Documentation, https://EnhancerAI.readthedocs.io/
Project-URL: Source, https://github.com/aertslab/EnhancerAI/
Project-URL: Home-page, https://github.com/aertslab/EnhancerAI/
Author: Lukas Mahieu
Maintainer-email: Lukas Mahieu <lukas.mahieu@kuleuven.be>
License: MIT License
License-File: LICENSE
Requires-Python: >=3.9
Requires-Dist: anndata
Requires-Dist: pandas
Requires-Dist: session-info
Provides-Extra: dev
Requires-Dist: pre-commit; extra == 'dev'
Requires-Dist: twine>=4.0.2; extra == 'dev'
Provides-Extra: doc
Requires-Dist: docutils!=0.18.*,!=0.19.*,>=0.8; extra == 'doc'
Requires-Dist: ipykernel; extra == 'doc'
Requires-Dist: ipython; extra == 'doc'
Requires-Dist: myst-nb; extra == 'doc'
Requires-Dist: pandas; extra == 'doc'
Requires-Dist: sphinx-autodoc-typehints; extra == 'doc'
Requires-Dist: sphinx-book-theme>=1.0.0; extra == 'doc'
Requires-Dist: sphinx-copybutton; extra == 'doc'
Requires-Dist: sphinx>=4; extra == 'doc'
Requires-Dist: sphinxcontrib-bibtex>=1.0.0; extra == 'doc'
Requires-Dist: sphinxext-opengraph; extra == 'doc'
Provides-Extra: test
Requires-Dist: coverage; extra == 'test'
Requires-Dist: pytest; extra == 'test'
